fdleaky/__init__.py
fdleaky/__main__.py
fdleaky/dir_fd_info_store.py
fdleaky/fd.py
fdleaky/fd_info.py
fdleaky/fd_info_factory.py
fdleaky/fd_info_store.py
fdleaky/fd_tracker.py
fdleaky-0.0.11.dist-info/METADATA
fdleaky-0.0.11.dist-info/WHEEL
fdleaky-0.0.11.dist-info/RECORD
