Metadata-Version: 2.3
Name: fdleaky
Version: 0.0.11
Summary: A simple IOC / Dependency injection micro framework for Python.
License: MIT
Author: Tim O'Farrell
Author-email: tofarr@gmail.com
Requires-Python: >=3.11,<4.0
Classifier: License :: OSI Approved :: MIT License
Classifier: Operating System :: OS Independent
Classifier: Programming Language :: Python :: 3
Classifier: Programming Language :: Python :: 3.11
Classifier: Programming Language :: Python :: 3.12
Classifier: Programming Language :: Python :: 3.13
Requires-Dist: fastapi (>=0.115.11,<0.116.0)
Requires-Dist: uvicorn (>=0.34.0,<0.35.0)
Project-URL: Repository, https://github.com/tofarr/fdleaky
